alpha_vantage/__init__.py
alpha_vantage/alphavantage.py
alpha_vantage/cryptocurrencies.py
alpha_vantage/foreignexchange.py
alpha_vantage/fundamentaldata.py
alpha_vantage/sectorperformance.py
alpha_vantage/techindicators.py
alpha_vantage/timeseries.py
alpha_vantage/async_support/__init__.py
alpha_vantage/async_support/alphavantage.py
alpha_vantage/async_support/cryptocurrencies.py
alpha_vantage/async_support/foreignexchange.py
alpha_vantage/async_support/fundamentaldata.py
alpha_vantage/async_support/sectorperformance.py
alpha_vantage/async_support/techindicators.py
alpha_vantage/async_support/timeseries.py
alpha_vantage/errors/__init__.py
alpha_vantage/errors/ratelimiterror.py
alpha_vantage/helpers/__init__.py
alpha_vantage/helpers/asyncbaseurlsession.py
alpha_vantage/helpers/baseurlsession.py
alpha_vantage/helpers/pipy_rst_convert.py
dhoeppe_alpha_vantage-2.4.2.dist-info/LICENSE.txt
dhoeppe_alpha_vantage-2.4.2.dist-info/METADATA
dhoeppe_alpha_vantage-2.4.2.dist-info/WHEEL
dhoeppe_alpha_vantage-2.4.2.dist-info/top_level.txt
dhoeppe_alpha_vantage-2.4.2.dist-info/RECORD
