Metadata-Version: 2.1
Name: dhoeppe-alpha-vantage
Version: 2.4.2
Summary: Python module to get stock data from the Alpha Vantage API
Home-page: https://github.com/dhoeppe/alpha_vantage
Author: Romel J. Torres
Author-email: romel.torres@gmail.com
License: MIT
Keywords: stocks,market,finance,alpha_vantage,quotes,shares,crypto,cryptocurrency
Platform: UNKNOWN
Classifier: Development Status :: 5 - Production/Stable
Classifier: Intended Audience :: Developers
Classifier: Topic :: Office/Business :: Financial :: Investment
Classifier: License :: OSI Approved :: MIT License
Classifier: Programming Language :: Python :: 3.6
Classifier: Programming Language :: Python :: 3.7
Classifier: Programming Language :: Python :: 3.8
Classifier: Programming Language :: Python :: 3.9
Requires-Dist: aiohttp
Requires-Dist: requests
